AUTHORS
ChangeLog
README.rst
requirements.txt
setup.cfg
setup.py
amvernoncal/__init__.py
amvernoncal/gcal_to_xlsx.py
amvernoncal.egg-info/PKG-INFO
amvernoncal.egg-info/SOURCES.txt
amvernoncal.egg-info/dependency_links.txt
amvernoncal.egg-info/entry_points.txt
amvernoncal.egg-info/not-zip-safe
amvernoncal.egg-info/pbr.json
amvernoncal.egg-info/requires.txt
amvernoncal.egg-info/top_level.txt
amvernoncal/classification/__init__.py
amvernoncal/classification/classifier.py
amvernoncal/classification/constants_and_regexes.py
amvernoncal/gui/__init__.py
amvernoncal/gui/dialogs.py
amvernoncal/gui/main.py
amvernoncal/gui/menubar.py
amvernoncal/gui/toolbar.py
amvernoncal/jsonproc/__init__.py
amvernoncal/jsonproc/cal_cleaner.py
amvernoncal/jsonproc/process_cal.py
amvernoncal/pdf_grabber/link_grabber.py
amvernoncal/pdfproc/__init__.py
amvernoncal/pdfproc/pdf_to_json.py
amvernoncal/pdfproc/tabula-cli.jar
docs/Makefile
docs/source/conf.py
docs/source/index.rst