Metadata-Version: 2.1
Name: amvernoncal
Version: 0.0.3.dev5
Summary: A package that uses natural language processing to convert PDF calendars to JSONs and to convert Google Calendar events to Excel files
Home-page: http://github.com/vincentchov/amvernon-cal
Author: Vincent Chov
Author-email: vincent.chov@uconn.edu
License: MIT
Platform: UNKNOWN
Classifier: Development Status :: 4 - Beta
Classifier: Environment :: Console
Classifier: Intended Audience :: Developers
Classifier: Intended Audience :: Information Technology
Classifier: Operating System :: OS Independent
Classifier: Programming Language :: Python
Provides-Extra: levenshtein
